{"last_node_id": 37, "last_link_id": 81, "nodes": [{"id": 6, "type": "EmptyLatentImage", "pos": {"0": 553, "1": 475}, "size": {"0": 315, "1": 106}, "flags": {}, "order": 0, "mode": 0, "inputs": [], "outputs": [{"name": "LATENT", "type": "LATENT", "links": [75], "slot_index": 0, "shape": 3}], "properties": {"Node name for S&R": "EmptyLatentImage"}, "widgets_values": [1024, 1024, 1]}, {"id": 8, "type": "VAELoader", "pos": {"0": 1048, "1": 347}, "size": {"0": 315, "1": 58}, "flags": {}, "order": 1, "mode": 0, "inputs": [], "outputs": [{"name": "VAE", "type": "VAE", "links": [59], "slot_index": 0, "shape": 3}], "properties": {"Node name for S&R": "VAELoader"}, "widgets_values": ["ae.safetensors"]}, {"id": 35, "type": "FluxLoraLoader", "pos": {"0": 1020, "1": -158}, "size": {"0": 315, "1": 82}, "flags": {}, "order": 2, "mode": 0, "inputs": [{"name": "model", "type": "MODEL", "link": null}], "outputs": [{"name": "MODEL", "type": "MODEL", "links": null, "shape": 3}], "properties": {"Node name for S&R": "FluxLoraLoader"}, "widgets_values": ["anime_lora.safetensors", 1]}, {"id": 33, "type": "ImageScale", "pos": {"0": -80, "1": -148}, "size": {"0": 315, "1": 130}, "flags": {}, "order": 9, "mode": 0, "inputs": [{"name": "image", "type": "IMAGE", "link": 72, "slot_index": 0}], "outputs": [{"name": "IMAGE", "type": "IMAGE", "links": [73], "slot_index": 0, "shape": 3}], "properties": {"Node name for S&R": "ImageScale"}, "widgets_values": ["nearest-exact", 1024, 1024, "disabled"]}, {"id": 7, "type": "VAEDecode", "pos": {"0": 1346, "1": -128}, "size": {"0": 210, "1": 46}, "flags": {}, "order": 14, "mode": 0, "inputs": [{"name": "samples", "type": "LATENT", "link": 6, "slot_index": 0}, {"name": "vae", "type": "VAE", "link": 59}], "outputs": [{"name": "IMAGE", "type": "IMAGE", "links": [76], "slot_index": 0, "shape": 3}], "properties": {"Node name for S&R": "VAEDecode"}, "widgets_values": []}, {"id": 19, "type": "CLIPTextEncodeFlux", "pos": {"0": 142, "1": 288}, "size": {"0": 400, "1": 200}, "flags": {}, "order": 11, "mode": 0, "inputs": [{"name": "clip", "type": "CLIP", "link": 79, "slot_index": 0}], "outputs": [{"name": "CONDITIONING", "type": "CONDITIONING", "links": [26], "slot_index": 0, "shape": 3}], "properties": {"Node name for S&R": "CLIPTextEncodeFlux"}, "widgets_values": ["", "", 4]}, {"id": 29, "type": "ImageCrop", "pos": {"0": -76, "1": 74}, "size": {"0": 315, "1": 130}, "flags": {}, "order": 8, "mode": 0, "inputs": [{"name": "image", "type": "IMAGE", "link": 55, "slot_index": 0}], "outputs": [{"name": "IMAGE", "type": "IMAGE", "links": [], "slot_index": 0, "shape": 3}], "properties": {"Node name for S&R": "ImageCrop"}, "widgets_values": [1024, 512, 4, 4]}, {"id": 32, "type": "LoadFluxIPAdapter", "pos": {"0": 313, "1": 147}, "size": {"0": 315, "1": 106}, "flags": {}, "order": 3, "mode": 0, "inputs": [], "outputs": [{"name": "ipadapterFlux", "type": "IP_ADAPTER_FLUX", "links": [65], "slot_index": 0, "shape": 3}], "properties": {"Node name for S&R": "LoadFluxIPAdapter"}, "widgets_values": ["flux-ip-adapter.safetensors", "clipvision_flux.safetensors", "CPU"]}, {"id": 4, "type": "DualCLIPLoader", "pos": {"0": -455, "1": -15}, "size": {"0": 315, "1": 106}, "flags": {}, "order": 4, "mode": 0, "inputs": [], "outputs": [{"name": "CLIP", "type": "CLIP", "links": [77], "slot_index": 0, "shape": 3}], "properties": {"Node name for S&R": "DualCLIPLoader"}, "widgets_values": ["t5xxl_fp8_e4m3fn.safetensors", "clip_l.safetensors", "flux"]}, {"id": 10, "type": "UNETLoader", "pos": {"0": -426, "1": -181}, "size": {"0": 315, "1": 82}, "flags": {}, "order": 5, "mode": 0, "inputs": [], "outputs": [{"name": "MODEL", "type": "MODEL", "links": [80], "slot_index": 0, "shape": 3}], "properties": {"Node name for S&R": "UNETLoader"}, "widgets_values": ["flux1-dev-fp8-e4m3fn.safetensors", "fp8_e4m3fn"]}, {"id": 3, "type": "XlabsSampler", "pos": {"0": 893, "1": 76}, "size": {"0": 342.5999755859375, "1": 282}, "flags": {}, "order": 13, "mode": 0, "inputs": [{"name": "model", "type": "MODEL", "link": 62, "slot_index": 0}, {"name": "conditioning", "type": "CONDITIONING", "link": 18}, {"name": "neg_conditioning", "type": "CONDITIONING", "link": 26}, {"name": "latent_image", "type": "LATENT", "link": 75, "shape": 7}, {"name": "controlnet_condition", "type": "ControlNetCondition", "link": null, "shape": 7}], "outputs": [{"name": "latent", "type": "LATENT", "links": [6], "shape": 3}], "properties": {"Node name for S&R": "XlabsSampler"}, "widgets_values": [132332768296188, "fixed", 25, 1, 3.5, 0, 1]}, {"id": 27, "type": "ApplyFluxIPAdapter", "pos": {"0": 642, "1": 248}, "size": {"0": 210, "1": 98}, "flags": {}, "order": 12, "mode": 0, "inputs": [{"name": "model", "type": "MODEL", "link": 81, "slot_index": 0}, {"name": "ip_adapter_flux", "type": "IP_ADAPTER_FLUX", "link": 65}, {"name": "image", "type": "IMAGE", "link": 73, "slot_index": 2}], "outputs": [{"name": "MODEL", "type": "MODEL", "links": [62], "slot_index": 0, "shape": 3}], "properties": {"Node name for S&R": "ApplyFluxIPAdapter"}, "widgets_values": [0.75]}, {"id": 5, "type": "CLIPTextEncodeFlux", "pos": {"0": 428, "1": -169}, "size": {"0": 400, "1": 200}, "flags": {}, "order": 10, "mode": 0, "inputs": [{"name": "clip", "type": "CLIP", "link": 78, "slot_index": 0}], "outputs": [{"name": "CONDITIONING", "type": "CONDITIONING", "links": [18], "slot_index": 0, "shape": 3}], "properties": {"Node name for S&R": "CLIPTextEncodeFlux"}, "widgets_values": ["\"An elegant redhead supermodel struts confidently down a luxurious fashion runway. Her long, flowing hair catches the soft, diffused lighting, creating a halo effect around her. She wears a shimmering, high-fashion gown that accentuates her graceful silhouette. The background features an opulent runway with golden accents and a captivated audience. The scene is rendered in a photorealistic and glamorous style, with vibrant colors and intricate details. Technical parameters: 8k resolution", "\"An elegant redhead supermodel struts confidently down a luxurious fashion runway. Her long, flowing hair catches the soft, diffused lighting, creating a halo effect around her. She wears a shimmering, high-fashion gown that accentuates her graceful silhouette. The background features an opulent runway with golden accents and a captivated audience. The scene is rendered in a photorealistic and glamorous style, with vibrant colors and intricate details. Technical parameters: 8k resolution", 4]}, {"id": 36, "type": "PreviewImage", "pos": {"0": 831, "1": -1242}, "size": {"0": 865.8053588867188, "1": 863.5560913085938}, "flags": {}, "order": 15, "mode": 0, "inputs": [{"name": "images", "type": "IMAGE", "link": 76, "slot_index": 0}], "outputs": [], "properties": {"Node name for S&R": "PreviewImage"}, "widgets_values": []}, {"id": 16, "type": "LoadImage", "pos": {"0": -111, "1": -1234}, "size": [922.6040167236325, 830.5228271484372], "flags": {}, "order": 6, "mode": 0, "inputs": [], "outputs": [{"name": "IMAGE", "type": "IMAGE", "links": [55, 72], "slot_index": 0, "shape": 3}, {"name": "MASK", "type": "MASK", "links": null, "shape": 3}], "properties": {"Node name for S&R": "LoadImage"}, "widgets_values": ["GX8l6R2XkAAR7-j.jpeg", "image"]}, {"id": 37, "type": "LoraLoader", "pos": {"0": -53, "1": -311}, "size": {"0": 315, "1": 126}, "flags": {}, "order": 7, "mode": 0, "inputs": [{"name": "model", "type": "MODEL", "link": 80}, {"name": "clip", "type": "CLIP", "link": 77}], "outputs": [{"name": "MODEL", "type": "MODEL", "links": [81], "slot_index": 0}, {"name": "CLIP", "type": "CLIP", "links": [78, 79], "slot_index": 1}], "properties": {"Node name for S&R": "LoraLoader"}, "widgets_values": ["flux/meeca/meeca-000012.safetensors", 0.75, 0.75]}], "links": [[6, 3, 0, 7, 0, "LATENT"], [18, 5, 0, 3, 1, "CONDITIONING"], [26, 19, 0, 3, 2, "CONDITIONING"], [55, 16, 0, 29, 0, "IMAGE"], [59, 8, 0, 7, 1, "VAE"], [62, 27, 0, 3, 0, "MODEL"], [65, 32, 0, 27, 1, "IP_ADAPTER_FLUX"], [72, 16, 0, 33, 0, "IMAGE"], [73, 33, 0, 27, 2, "IMAGE"], [75, 6, 0, 3, 3, "LATENT"], [76, 7, 0, 36, 0, "IMAGE"], [77, 4, 0, 37, 1, "CLIP"], [78, 37, 1, 5, 0, "CLIP"], [79, 37, 1, 19, 0, "CLIP"], [80, 10, 0, 37, 0, "MODEL"], [81, 37, 0, 27, 0, "MODEL"]], "groups": [], "config": {}, "extra": {}, "version": 0.4}